pyacmecli/__init__.py
pyacmecli/__main__.py
pyacmecli/acme/__init__.py
pyacmecli/acme/helper.py
pyacmecli/common/__init__.py
pyacmecli/common/certificates.py
pyacmecli/happylog/__init__.py
pyacmecli/tls/__init__.py
pyacmecli/tls/ssl_object.py
pyacmecli/webhooks/__init__.py
pyacmecli/webhooks/acmedns.py
pyacmecli/webhooks/arvancloud.py
pyacmecli/webhooks/base.py
pyacmecli/webhooks/cloudflare.py
pyacmecli/webhooks/func_helper.py
pyacmecli-0.1.7.dist-info/licenses/LICENSE
pyacmecli-0.1.7.dist-info/METADATA
pyacmecli-0.1.7.dist-info/WHEEL
pyacmecli-0.1.7.dist-info/entry_points.txt
pyacmecli-0.1.7.dist-info/top_level.txt
pyacmecli-0.1.7.dist-info/RECORD
