Metadata-Version: 2.4
Name: pyacmecli
Version: 0.1.7
License-File: LICENSE
Requires-Dist: build==1.3.0
Requires-Dist: certifi==2025.10.5
Requires-Dist: cffi==2.0.0
Requires-Dist: charset-normalizer==3.4.3
Requires-Dist: click==8.3.0
Requires-Dist: cryptography==46.0.2
Requires-Dist: dnspython==2.8.0
Requires-Dist: docutils==0.22.3
Requires-Dist: filelock==3.20.0
Requires-Dist: id==1.5.0
Requires-Dist: idna==3.10
Requires-Dist: jaraco-classes==3.4.0
Requires-Dist: jaraco-context==6.0.1
Requires-Dist: jaraco-functools==4.3.0
Requires-Dist: jeepney==0.9.0
Requires-Dist: josepy==2.1.0
Requires-Dist: keyring==25.7.0
Requires-Dist: markdown-it-py==4.0.0
Requires-Dist: mdurl==0.1.2
Requires-Dist: more-itertools==10.8.0
Requires-Dist: nh3==0.3.2
Requires-Dist: packaging==25.0
Requires-Dist: pycparser==2.23
Requires-Dist: pygments==2.19.2
Requires-Dist: pyopenssl==25.3.0
Requires-Dist: pyproject-hooks==1.2.0
Requires-Dist: pyrfc3339==2.1.0
Requires-Dist: readme-renderer==44.0
Requires-Dist: requests==2.32.5
Requires-Dist: requests-file==2.1.0
Requires-Dist: requests-toolbelt==1.0.0
Requires-Dist: rfc3986==2.0.0
Requires-Dist: rich==14.2.0
Requires-Dist: secretstorage==3.5.0
Requires-Dist: setuptools==80.9.0
Requires-Dist: tabulate==0.9.0
Requires-Dist: tldextract==5.3.0
Requires-Dist: twine==6.2.0
Requires-Dist: typing-extensions==4.15.0
Requires-Dist: urllib3==2.5.0
Requires-Dist: validators==0.35.0
Dynamic: license-file
